pyduofern/__init__.py
pyduofern/definitions.py
pyduofern/duofern.py
pyduofern/duofern_stick.py
pyduofern/exceptions.py
pyduofern-0.36.2.data/scripts/duofern_cli.py
pyduofern-0.36.2.dist-info/METADATA
pyduofern-0.36.2.dist-info/WHEEL
pyduofern-0.36.2.dist-info/top_level.txt
pyduofern-0.36.2.dist-info/RECORD
