Metadata-Version: 2.1
Name: pyduofern
Version: 0.36.2
Summary: Library for controlling Rademacher DuoFern actors using python. Requires the RademacherDuofern USB Stick Art.-Nr.: 70000093
Home-page: https://github.com/gluap/pyduofern
Author: Paul Görgen
Author-email: pypi@pgoergen.de
License: GPL-2.0
Classifier: Development Status :: 3 - Alpha
Classifier: License :: OSI Approved :: GNU General Public License v2 (GPLv2)
Classifier: Programming Language :: Python :: 3.4
Requires-Dist: pyserial
Requires-Dist: pyserial-asyncio
